django_common_user_tenants/__init__.py
django_common_user_tenants/admin.py
django_common_user_tenants/apps.py
django_common_user_tenants/cache.py
django_common_user_tenants/clone.py
django_common_user_tenants/compat.py
django_common_user_tenants/log.py
django_common_user_tenants/models.py
django_common_user_tenants/routers.py
django_common_user_tenants/signals.py
django_common_user_tenants/tasks.py
django_common_user_tenants/urlresolvers.py
django_common_user_tenants/utils.py
django_common_user_tenants/files/__init__.py
django_common_user_tenants/files/storage.py
django_common_user_tenants/files/storages.py
django_common_user_tenants/management/__init__.py
django_common_user_tenants/management/commands/__init__.py
django_common_user_tenants/management/commands/clone_tenant.py
django_common_user_tenants/management/commands/collectstatic_schemas.py
django_common_user_tenants/management/commands/create_tenant.py
django_common_user_tenants/management/commands/create_tenant_superuser.py
django_common_user_tenants/management/commands/migrate.py
django_common_user_tenants/management/commands/migrate_schemas.py
django_common_user_tenants/management/commands/syncdb.py
django_common_user_tenants/management/commands/tenant_command.py
django_common_user_tenants/middleware/__init__.py
django_common_user_tenants/middleware/default.py
django_common_user_tenants/middleware/main.py
django_common_user_tenants/middleware/suspicious.py
django_common_user_tenants/migration_executors/__init__.py
django_common_user_tenants/migration_executors/base.py
django_common_user_tenants/migration_executors/multiproc.py
django_common_user_tenants/migration_executors/standard.py
django_common_user_tenants/permissions/__init__.py
django_common_user_tenants/permissions/backend.py
django_common_user_tenants/permissions/models.py
django_common_user_tenants/permissions/tests.py
django_common_user_tenants/permissions/utils.py
django_common_user_tenants/permissions/views.py
django_common_user_tenants-0.0.26.dist-info/LICENSE
django_common_user_tenants-0.0.26.dist-info/METADATA
django_common_user_tenants-0.0.26.dist-info/WHEEL
django_common_user_tenants-0.0.26.dist-info/top_level.txt
django_common_user_tenants-0.0.26.dist-info/RECORD
